{
  "name": "小白天枢",
  "version": "0.1.10",
  "versionCode": 110,
  "platform": "android-harmonyos",
  "packageName": "cn.xiaobaiai.agent.mobile",
  "signing": "debug",
  "storeReady": false,
  "storeMode": false,
  "minSdk": 23,
  "targetSdk": 35,
  "privacyPolicyUrl": "https://www.xiaobaiai.cn/privacy",
  "builtAt": "2026-05-19T22:44:04.525Z",
  "files": [
    {
      "name": "Xiaobai-Tianshu-0.1.10.apk",
      "size": 62094,
      "sha256": "5a0bee716238fbbe6b7605209deabcaa2bfb497e3f8dacf6e308f3cc2d995963"
    }
  ]
}
